pykg_spark/__init__.py
pykg_spark/hdfs_utilities/__init__.py
pykg_spark/hdfs_utilities/hdfs_reader.py
pykg_spark/pandas_udfs/__init__.py
pykg_spark/pandas_udfs/general_udfs.py
pykg_spark/pandas_udfs/general_udfs_base.py
pykg_spark-0.1.6.dist-info/LICENSE
pykg_spark-0.1.6.dist-info/WHEEL
pykg_spark-0.1.6.dist-info/METADATA
pykg_spark-0.1.6.dist-info/RECORD
