Metadata-Version: 2.1
Name: pykg-spark
Version: 0.1.6
Summary: ETL focused utilities library for PySpark
License: Apache-2.0
Author: Agung Setiaji
Author-email: mragungsetiaji@gmail.com
Requires-Python: >=3.6,<4.0
Classifier: License :: OSI Approved :: Apache Software License
Classifier: Programming Language :: Python :: 3
Classifier: Programming Language :: Python :: 3.6
Classifier: Programming Language :: Python :: 3.7
Classifier: Programming Language :: Python :: 3.8
Classifier: Programming Language :: Python :: 3.9
Requires-Dist: pandas (>=1.1.4,<2.0.0)
